Metadata-Version: 2.1
Name: oneNeuron-pypi-wongannnee
Version: 0.0.3
Summary: Small package for ANN implementation
Home-page: https://github.com/wongannnee/oneNeuron_pypi
Author: wongannnee
Author-email: wongannnee88@gmail.com
License: UNKNOWN
Project-URL: Bug Tracker, https://github.com/wongannnee/oneNeuron_pypi/issues
Platform: UNKNOWN
Classifier: Programming Language :: Python :: 3.7
Classifier: License :: OSI Approved :: MIT License
Classifier: Operating System :: OS Independent
Requires-Python: >=3.7
License-File: LICENSE
Requires-Dist: matplotlib
Requires-Dist: seaborn
Requires-Dist: numpy
Requires-Dist: pandas
Requires-Dist: PyYAML
Requires-Dist: tqdm
